tinysearch-0.5.0.dist-info/METADATA
tinysearch-0.5.0.dist-info/WHEEL
tinysearch-0.5.0.dist-info/licenses/LICENSE
tinysearch/__init__.py
tinysearch/analyzer.py
tinysearch/base/__init__.py
tinysearch/base/analyzer.py
tinysearch/document.py
tinysearch/index.py
tinysearch/search.py
tinysearch-0.5.0.dist-info/RECORD
