Metadata-Version: 2.1
Name: tinysearch
Version: 0.5.0
Summary: Tiny one-phase search engine
Keywords: search engine
Author-Email: Domagoj Marsic <dmars@protonmail.com>
License: Apache-2.0
Classifier: License :: OSI Approved :: Apache Software License
Classifier: Programming Language :: Python
Classifier: Programming Language :: Python :: 3
Project-URL: Homepage, https://github.com/dmarsic/tinysearch
Requires-Python: >=3.9
Requires-Dist: pystemmer>=2.2.0.1
